LICENSE
MANIFEST.in
README.md
package.json
setup.py
cada_dash_custom_radioitems/CadaDashCustomRadioitems.py
cada_dash_custom_radioitems/__init__.py
cada_dash_custom_radioitems/_imports_.py
cada_dash_custom_radioitems/cada_dash_custom_radioitems.min.js
cada_dash_custom_radioitems/cada_dash_custom_radioitems.min.js.map
cada_dash_custom_radioitems/metadata.json
cada_dash_custom_radioitems/package-info.json
cada_dash_custom_radioitems.egg-info/PKG-INFO
cada_dash_custom_radioitems.egg-info/SOURCES.txt
cada_dash_custom_radioitems.egg-info/dependency_links.txt
cada_dash_custom_radioitems.egg-info/top_level.txt