Metadata-Version: 1.0
Name: cada-dash-custom-radioitems
Version: 0.1.1
Summary: A Custom implementation of the Dash Radio items using Images as Radio Buttons
Home-page: UNKNOWN
Author: Pardon Chawatama <chawatamapardon@gmail.com>
Author-email: UNKNOWN
License: MIT
Platform: UNKNOWN
